Users/alin/.config/spfy/config.toml
spfy/__init__.py
spfy/client.py
spfy/config.toml
spfy/constants.py
spfy/exceptions.py
spfy/frange.py
spfy/log.py
spfy/result.py
spfy/server.py
spfy/sql.py
spfy/util.py
spfy/volume.py
spfy/wrapper.py
spfy/async/__init__.py
spfy/async/client.py
spfy/async/result.py
spfy/async/wrapper.py
spfy/asynch/__init__.py
spfy/asynch/client.py
spfy/asynch/result.py
spfy/asynch/wrapper.py
spfy/cache/__init__.py
spfy/cache/db.py
spfy/config/config.toml
spfy/config/develop.toml
spfy/config/test.toml
spfy/html/auth_message.html
spfy/html/login.html
spfy/mixins/__init__.py
spfy/mixins/auth.py
spfy/mixins/email.py
spfy/mixins/player.py
spfy/mixins/recommender.py
spfy/mixins/server.py
spfy/mixins/async/__init__.py
spfy/mixins/async/aiohttp_oauthlib.py
spfy/mixins/async/auth.py
spfy/mixins/async/player.py
spfy/mixins/async/recommender.py
spfy/mixins/asynch/__init__.py
spfy/mixins/asynch/aiohttp_oauthlib.py
spfy/mixins/asynch/auth.py
spfy/mixins/asynch/player.py
spfy/mixins/asynch/recommender.py
tests/__init__.py
spfy-3.10.0.dist-info/LICENSE-APACHE
spfy-3.10.0.dist-info/LICENSE-MIT
spfy-3.10.0.dist-info/METADATA
spfy-3.10.0.dist-info/WHEEL
spfy-3.10.0.dist-info/entry_points.txt
spfy-3.10.0.dist-info/top_level.txt
spfy-3.10.0.dist-info/RECORD
