Metadata-Version: 2.1
Name: spfy
Version: 3.10.0
Home-page: https://github.com/alin23/spfy
Author: Alin Panaitiu
Author-email: alin.p32@gmail.com
Maintainer: Alin Panaitiu
Maintainer-email: alin.p32@gmail.com
License: MIT/Apache-2.0
Keywords: spotify,spfy
Classifier: Development Status :: 4 - Beta
Classifier: Intended Audience :: Developers
Classifier: License :: OSI Approved :: MIT License
Classifier: License :: OSI Approved :: Apache Software License
Classifier: Natural Language :: English
Classifier: Operating System :: OS Independent
Classifier: Programming Language :: Python :: 3.6
Classifier: Programming Language :: Python :: Implementation :: CPython
Classifier: Programming Language :: Python :: Implementation :: PyPy
License-File: LICENSE-APACHE
License-File: LICENSE-MIT
Requires-Dist: addict
Requires-Dist: aiohttp
Requires-Dist: aioredis (<2.0.0)
Requires-Dist: async-generator
Requires-Dist: asyncpg
Requires-Dist: backoff
Requires-Dist: cachecontrol
Requires-Dist: cached-property
Requires-Dist: colorthief
Requires-Dist: fire
Requires-Dist: first
Requires-Dist: gunicorn
Requires-Dist: hug
Requires-Dist: kick (>=1.1.0)
Requires-Dist: lockfile
Requires-Dist: mailer
Requires-Dist: msgpack
Requires-Dist: oauthlib
Requires-Dist: pandas
Requires-Dist: pony
Requires-Dist: psycopg2-binary
Requires-Dist: pycountry
Requires-Dist: python-unsplash-async (>=1.0.4)
Requires-Dist: urllib3
Requires-Dist: requests
Requires-Dist: requests-oauthlib
Requires-Dist: tenacity
Requires-Dist: ujson
